cbpickaxe/__init__.py
cbpickaxe/animation.py
cbpickaxe/elemental_type.py
cbpickaxe/hoylake.py
cbpickaxe/item.py
cbpickaxe/misc_types.py
cbpickaxe/monster_form.py
cbpickaxe/move.py
cbpickaxe/py.typed
cbpickaxe/resource.py
cbpickaxe/translation_table.py
cbpickaxe_scripts/__init__.py
cbpickaxe_scripts/extract_translation.py
cbpickaxe_scripts/generate_docs.py
cbpickaxe_scripts/generate_monster_animations.py
cbpickaxe_scripts/get_move_users.py
cbpickaxe_scripts/templates/base.html
cbpickaxe_scripts/templates/index.html
cbpickaxe_scripts/templates/item.html
cbpickaxe_scripts/templates/monster_form.html
cbpickaxe_scripts/templates/move.html
cbpickaxe-0.1.2.dist-info/LICENSE
cbpickaxe-0.1.2.dist-info/METADATA
cbpickaxe-0.1.2.dist-info/WHEEL
cbpickaxe-0.1.2.dist-info/entry_points.txt
cbpickaxe-0.1.2.dist-info/top_level.txt
cbpickaxe-0.1.2.dist-info/RECORD
