Metadata-Version: 2.1
Name: cbpickaxe
Version: 0.1.2
Summary: A Python library and scripts for data mining the game Cassette Beasts.
Author: ExcaliburZero
License: MIT License
Project-URL: Changelog, https://github.com/ExcaliburZero/cbpickaxe/blob/master/CHANGELOG.md
Project-URL: Documentation, https://cbpickaxe.readthedocs.io/en/latest/
Project-URL: Homepage, https://github.com/ExcaliburZero/cbpickaxe
Project-URL: Issues, https://github.com/ExcaliburZero/cbpickaxe/issues
Project-URL: Repository, https://github.com/ExcaliburZero/cbpickaxe.git
Keywords: Cassette Beasts
Classifier: Development Status :: 3 - Alpha
Classifier: Programming Language :: Python
Classifier: Environment :: Console
Classifier: Intended Audience :: Developers
Classifier: License :: OSI Approved :: MIT License
Classifier: Programming Language :: Python :: 3.11
Classifier: Typing :: Typed
Requires-Python: >=3.11
License-File: LICENSE
Requires-Dist: godot-parser
Requires-Dist: smaz-py3 >=1.1.3
Requires-Dist: Jinja2
Requires-Dist: Pillow
Provides-Extra: test
Requires-Dist: black ; extra == 'test'
Requires-Dist: mypy ; extra == 'test'
Requires-Dist: pylint ; extra == 'test'
Requires-Dist: pytest ; extra == 'test'
